faker_to_kafka/__init__.py
faker_to_kafka/config_parse.py
faker_to_kafka/csv_generator.py
faker_to_kafka/generator_factory.py
faker_to_kafka/json_generator.py
faker_to_kafka/kafka_sender.py
faker_to_kafka/main.py
faker_to_kafka-0.0.1.dist-info/LICENSE
faker_to_kafka-0.0.1.dist-info/METADATA
faker_to_kafka-0.0.1.dist-info/WHEEL
faker_to_kafka-0.0.1.dist-info/top_level.txt
faker_to_kafka-0.0.1.dist-info/RECORD
